{
    "users": [
        {
            "login": "Islan",
            "pass": "1234ab",
            "nameAlias": "Islanzin"
        },
        {
            "login": "alee",
            "pass": "bizz",
            "nameAlias": "alee"
        },
        {
            "login": "pedro",
            "pass": "aaa",
            "nameAlias": "pedro"
        },
        {
            "login": "ape",
            "pass": "aaa",
            "nameAlias": "pedro"
        },
        {
            "login": "a",
            "pass": "pedro",
            "nameAlias": "pr"
        },
        {
            "login": "\u001b[Apedro",
            "pass": "pedro",
            "nameAlias": "pedro"
        },
        {
            "login": "dadadadaddadadadadadadadddddale",
            "pass": "alee123",
            "nameAlias": "dale"
        },
        {
            "login": "aleee",
            "pass": "biz",
            "nameAlias": "biz"
        }
    ],
    "count": 0
}